pyviennacl/__init__.py
pyviennacl/_viennacl.so
pyviennacl/linalg.py
pyviennacl/pycore.py
pyviennacl/util.py
pyviennacl/vclmath.py
pyviennacl/version.py
pyviennacl-1.0.3.dist-info/DESCRIPTION.rst
pyviennacl-1.0.3.dist-info/METADATA
pyviennacl-1.0.3.dist-info/pydist.json
pyviennacl-1.0.3.dist-info/RECORD
pyviennacl-1.0.3.dist-info/top_level.txt
pyviennacl-1.0.3.dist-info/WHEEL
